gateraid/__init__.py
gateraid/controlled_gates.py
gateraid/gate_base.py
gateraid/other_gates.py
gateraid/quantum_state.py
gateraid/utilities.py
GaterAid-1.0.3.dist-info/LICENSE
GaterAid-1.0.3.dist-info/METADATA
GaterAid-1.0.3.dist-info/WHEEL
GaterAid-1.0.3.dist-info/top_level.txt
GaterAid-1.0.3.dist-info/RECORD
