Metadata-Version: 2.1
Name: GaterAid
Version: 1.0.3
Summary: A package to abate the strait of applying a two-qubit gate         to a quantum state.
Author: Eleanor Kneip, Stasiu Wolanski, Joel the intern
Author-email: eleanor.kneip.24@ucl.ac.uk,         stanislaw.wolanski.24@ucl.ac.uk, joel.mills.24@ucl.ac.uk
Project-URL: Documentation, https://statuesque-smakager-de86a9.netlify.app
Project-URL: Source, https://github.com/QC2-python-SE/QWACOBEC
Classifier: Programming Language :: Python :: 3
Classifier: License :: OSI Approved :: MIT License
Classifier: Operating System :: OS Independent
Requires-Python: >=3.6
License-File: LICENSE
Requires-Dist: numpy>=2.0.0
